Metadata-Version: 1.0
Name: app6995
Version: 0.114567
Summary: operation & greeting library
Home-page: UNKNOWN
Author: UNKNOWN
Author-email: piyush@gmail.com
License: UNKNOWN
Platform: UNKNOWN
